Metadata-Version: 2.1
Name: darkfunctions
Version: 0.0.1
Summary: blackhat hacking modules
Home-page: UNKNOWN
Author: iris
Author-email: sirpurchasehelp@gmail.com
License: MIT
Keywords: drk
Platform: UNKNOWN
Classifier: Development Status :: 5 - Production/Stable
Classifier: Intended Audience :: Education
Classifier: Operating System :: Microsoft :: Windows :: Windows 10
Classifier: License :: OSI Approved :: MIT License
Classifier: Programming Language :: Python :: 3
License-File: LICENCE.txt
